flask_parameter_validation/__init__.py
flask_parameter_validation/docs_blueprint.py
flask_parameter_validation/parameter_validation.py
flask_parameter_validation/exceptions/__init__.py
flask_parameter_validation/exceptions/exceptions.py
flask_parameter_validation/parameter_types/__init__.py
flask_parameter_validation/parameter_types/file.py
flask_parameter_validation/parameter_types/form.py
flask_parameter_validation/parameter_types/json.py
flask_parameter_validation/parameter_types/multi_source.py
flask_parameter_validation/parameter_types/parameter.py
flask_parameter_validation/parameter_types/query.py
flask_parameter_validation/parameter_types/route.py
flask_parameter_validation/templates/fpv_default_docs.html
Flask_Parameter_Validation-2.4.0.dist-info/METADATA
Flask_Parameter_Validation-2.4.0.dist-info/WHEEL
Flask_Parameter_Validation-2.4.0.dist-info/top_level.txt
Flask_Parameter_Validation-2.4.0.dist-info/RECORD
