Metadata-Version: 2.1
Name: Flask-Parameter-Validation
Version: 2.4.0
Summary: Get and validate all Flask input parameters with ease.
Home-page: https://github.com/Ge0rg3/flask-parameter-validation
Author: George Omnet
Author-email: flaskparametervalidation@georgeom.net
License: MIT
Platform: any
Classifier: Environment :: Web Environment
Classifier: Intended Audience :: Developers
Classifier: License :: OSI Approved :: MIT License
Classifier: Operating System :: OS Independent
Classifier: Programming Language :: Python
Classifier: Programming Language :: Python :: 3
Classifier: Programming Language :: Python :: 3.9
Classifier: Programming Language :: Python :: 3.10
Classifier: Programming Language :: Python :: 3.11
Classifier: Programming Language :: Python :: 3.12
Classifier: Development Status :: 5 - Production/Stable
Classifier: Framework :: Flask
Classifier: Topic :: Software Development :: Documentation
Classifier: Topic :: File Formats :: JSON :: JSON Schema
Classifier: Topic :: Internet :: WWW/HTTP :: Dynamic Content
Classifier: Topic :: Software Development :: Libraries :: Python Modules
Requires-Python: >=3.9,<3.13
Requires-Dist: Flask
Requires-Dist: flask[async]
Requires-Dist: python-dateutil
Requires-Dist: jsonschema
